Workbook

Sheet Premissas
A1: PT 540 - Provisao para abandono de pocos (ARO) - premissas e dados publicos
A2: PetroReconcavo S.A. - consolidado - R$ mil | Preparador: matricula 211059370 | 24/10/2026 | Revisao: ______ (nao preenchido)
A4: Item | B4: Valor | C4: Fonte / classificacao
A5: Taxa de desconto nominal 2025 | B5: 0.1056 | C5: NE 3.3 F01 - REALIZADO
A6: Inflacao 2025 | B6: 0.0356 | C6: NE 3.3 F01 - REALIZADO
A7: Taxa de desconto nominal 2024 | B7: 0.1092 | C7: NE 3.3 F01 - REALIZADO
A8: Inflacao 2024 | B8: 0.0366 | C8: NE 3.3 F01 - REALIZADO
A9: Saldo da provisao 31/12/2025 | B9: 145192 | C9: NE 13.1 F01 - REALIZADO
A10: parcela circulante 31/12/2025 | B10: 4728 | C10: NE 13.1 F01
A11: Saldo da provisao 31/12/2024 | B11: 136972 | C11: NE 13.1 F01 / NE 14 F07
A12: parcela circulante 31/12/2024 | B12: 342 | C12: NE 14 F07 (DF 2024)
A13: Materialidade para execucao (ME) | B13: 20475 | C13: PT 320
A14: Materialidade global (MG) | B14: 31500 | C14: PT 320

Sheet Retrospectiva_item14
A1: Movimentacao 2025 e revisao retrospectiva (NBC TA 540 item 14) - REALIZADO COM EVIDENCIA PUBLICA
A2: PetroReconcavo S.A. - consolidado - R$ mil | Preparador: matricula 211059370 | 24/10/2026 | Revisao: ______ (nao preenchido)
A4: Movimentacao 2025 (NE 13.1 consolidado) | B4: Valor | D4: Observacao
A5: Saldo 31/12/2024 | B5: =Premissas!B11 -> 136972
A6: Constituicao | B6: 8383
A7: Reversao | B7: -265
A8: Atualizacao (unwinding) | B8: 14958
A9: Baixas (abandonos realizados) | B9: -14856
A10: Saldo recalculado 31/12/2025 | B10: =SUM(B5:B9) -> 145192 | D10: Deve igualar a NE 13.1
A11: Saldo publicado 31/12/2025 | B11: =Premissas!B9 -> 145192
A12: Diferenca | B12: =B10-B11 -> 0 | D12: Zero = movimentacao fecha
A14: Recalculos | B14: Esperado | C14: Publicado | D14: Leitura
A15: Atualizacao 2025 = saldo 2024 x taxa nominal 2024 | B15: =Premissas!B11*Premissas!B7 -> 14957.342 | C15: =B8 -> 14958 | D15: Unwinding coerente com a taxa de 2024
A16: Baixas 2025 x parcela circulante estimada em 31/12/2024 | B16: =Premissas!B12 -> 342 | C16: =-B9 -> 14856 | D16: Baixas realizadas muito acima do previsto como circulante
A17: Multiplo baixas realizadas / circulante previsto | B17: =C16/B16 -> 43.438596 | D17: Indicador de falha na estimativa de EPOCA (A55-A60); ver PT 540
A18: Baixas 2025 x parcela circulante de 31/12/2025 | B18: =Premissas!B10 -> 4728 | C18: =-B9 -> 14856 | D18: Se o padrao se repetir, o circulante de 2025 pode estar subestimado (classificacao)
A19: Taxa real implicita 2025 = (1+r)/(1+pi)-1 | B19: =(1+Premissas!B5)/(1+Premissas!B6)-1 -> 0.067593666 | D19: Queda da taxa real aumenta a provisao
A20: Taxa real implicita 2024 | B20: =(1+Premissas!B7)/(1+Premissas!B8)-1 -> 0.070036658 | D20: Direcao da mudanca de premissa: AUMENTA o passivo (nao indica vies para reduzir)

Sheet Cronograma_SIMULADO
A1: Cronograma SINTETICO de desembolsos calibrado ao saldo publicado - SIMULADO PARA FINS DIDATICOS
A2: PetroReconcavo S.A. - consolidado - R$ mil | Preparador: matricula 211059370 | 24/10/2026 | Revisao: ______ (nao preenchido)
A3: A companhia nao divulga o cronograma. Perfil: 2026 = parcela circulante; 2027-2050 triangular com pico em 2040 (~14,8 anos de reservas 1P / producao). Custo em moeda de 31/12/2025.
D4: r=0.1056; pi=0.0356; x1.0; desloc 0 | E4: r=0.1156; pi=0.0356; x1.0; desloc 0 | F4: r=0.0956; pi=0.0356; x1.0; desloc 0 | G4: r=0.1056; pi=0.0456; x1.0; desloc 0 | H4: r=0.1056; pi=0.0256; x1.0; desloc 0 | I4: r=0.0956; pi=0.0456; x1.0; desloc 0 | J4: r=0.1056; pi=0.0356; x1.01; desloc 0 | K4: r=0.1056; pi=0.0356; x1.1; desloc 0 | L4: r=0.1056; pi=0.0356; x1.0; desloc -2 | M4: r=0.1092; pi=0.0366; x1.0; desloc 0
A5: Ano | B5: t | C5: Custo (moeda 2025) | D5: Base (NE 3.3: 10,56% / 3,56%) | E5: Taxa de desconto +1 p.p. (11,56%) | F5: Taxa de desconto -1 p.p. (9,56%) | G5: Inflacao +1 p.p. (4,56%) | H5: Inflacao -1 p.p. (2,56%) | I5: Pior combinacao: taxa -1 p.p. e inflacao +1 p.p. | J5: Custos +1% (sensibilidade de 1% - aula) | K5: Custos +10% | L5: Antecipacao de 2 anos no abandono | M5: Premissas de 2024 (10,92% / 3,66%) sobre o mesmo cronograma
A6: 2026 | B6: =A6-2025 -> 1 | C6: 5047.5829 | D6: =C6*1*(1+0.0356)^MAX(1,B6+(0))/(1+0.1056)^MAX(1,B6+(0)) -> 4728 | E6: =C6*1*(1+0.0356)^MAX(1,B6+(0))/(1+0.1156)^MAX(1,B6+(0)) -> 4685.6192 | F6: =C6*1*(1+0.0356)^MAX(1,B6+(0))/(1+0.0956)^MAX(1,B6+(0)) -> 4771.1544 | G6: =C6*1*(1+0.0456)^MAX(1,B6+(0))/(1+0.1056)^MAX(1,B6+(0)) -> 4773.6547 | H6: =C6*1*(1+0.0256)^MAX(1,B6+(0))/(1+0.1056)^MAX(1,B6+(0)) -> 4682.3453 | I6: =C6*1*(1+0.0456)^MAX(1,B6+(0))/(1+0.0956)^MAX(1,B6+(0)) -> 4817.2258 | J6: =C6*1.01*(1+0.0356)^MAX(1,B6+(0))/(1+0.1056)^MAX(1,B6+(0)) -> 4775.28 | K6: =C6*1.1*(1+0.0356)^MAX(1,B6+(0))/(1+0.1056)^MAX(1,B6+(0)) -> 5200.8 | L6: =C6*1*(1+0.0356)^MAX(1,B6+(-2))/(1+0.1056)^MAX(1,B6+(-2)) -> 4728 | M6: =C6*1*(1+0.0366)^MAX(1,B6+(0))/(1+0.1092)^MAX(1,B6+(0)) -> 4717.2055
A7: 2027 | B7: =A7-2025 -> 2 | C7: 1896.1973 | D7: =C7*1*(1+0.0356)^MAX(1,B7+(0))/(1+0.1056)^MAX(1,B7+(0)) -> 1663.6867 | E7: =C7*1*(1+0.0356)^MAX(1,B7+(0))/(1+0.1156)^MAX(1,B7+(0)) -> 1633.9945 | F7: =C7*1*(1+0.0356)^MAX(1,B7+(0))/(1+0.0956)^MAX(1,B7+(0)) -> 1694.1957 | G7: =C7*1*(1+0.0456)^MAX(1,B7+(0))/(1+0.1056)^MAX(1,B7+(0)) -> 1695.9718 | H7: =C7*1*(1+0.0256)^MAX(1,B7+(0))/(1+0.1056)^MAX(1,B7+(0)) -> 1631.7119 | I7: =C7*1*(1+0.0456)^MAX(1,B7+(0))/(1+0.0956)^MAX(1,B7+(0)) -> 1727.0727 | J7: =C7*1.01*(1+0.0356)^MAX(1,B7+(0))/(1+0.1056)^MAX(1,B7+(0)) -> 1680.3236 | K7: =C7*1.1*(1+0.0356)^MAX(1,B7+(0))/(1+0.1056)^MAX(1,B7+(0)) -> 1830.0554 | L7: =C7*1*(1+0.0356)^MAX(1,B7+(-2))/(1+0.1056)^MAX(1,B7+(-2)) -> 1776.1414 | M7: =C7*1*(1+0.0366)^MAX(1,B7+(0))/(1+0.1092)^MAX(1,B7+(0)) -> 1656.0987
A8: 2028 | B8: =A8-2025 -> 3 | C8: 3792.3946 | D8: =C8*1*(1+0.0356)^MAX(1,B8+(0))/(1+0.1056)^MAX(1,B8+(0)) -> 3116.704 | E8: =C8*1*(1+0.0356)^MAX(1,B8+(0))/(1+0.1156)^MAX(1,B8+(0)) -> 3033.6406 | F8: =C8*1*(1+0.0356)^MAX(1,B8+(0))/(1+0.0956)^MAX(1,B8+(0)) -> 3202.8277 | G8: =C8*1*(1+0.0456)^MAX(1,B8+(0))/(1+0.1056)^MAX(1,B8+(0)) -> 3207.8655 | H8: =C8*1*(1+0.0256)^MAX(1,B8+(0))/(1+0.1056)^MAX(1,B8+(0)) -> 3027.2861 | I8: =C8*1*(1+0.0456)^MAX(1,B8+(0))/(1+0.0956)^MAX(1,B8+(0)) -> 3296.5083 | J8: =C8*1.01*(1+0.0356)^MAX(1,B8+(0))/(1+0.1056)^MAX(1,B8+(0)) -> 3147.871 | K8: =C8*1.1*(1+0.0356)^MAX(1,B8+(0))/(1+0.1056)^MAX(1,B8+(0)) -> 3428.3744 | L8: =C8*1*(1+0.0356)^MAX(1,B8+(-2))/(1+0.1056)^MAX(1,B8+(-2)) -> 3552.2828 | M8: =C8*1*(1+0.0366)^MAX(1,B8+(0))/(1+0.1092)^MAX(1,B8+(0)) -> 3095.4055
A9: 2029 | B9: =A9-2025 -> 4 | C9: 5688.592 | D9: =C9*1*(1+0.0356)^MAX(1,B9+(0))/(1+0.1056)^MAX(1,B9+(0)) -> 4379.0593 | E9: =C9*1*(1+0.0356)^MAX(1,B9+(0))/(1+0.1156)^MAX(1,B9+(0)) -> 4224.1461 | F9: =C9*1*(1+0.0356)^MAX(1,B9+(0))/(1+0.0956)^MAX(1,B9+(0)) -> 4541.1396 | G9: =C9*1*(1+0.0456)^MAX(1,B9+(0))/(1+0.1056)^MAX(1,B9+(0)) -> 4550.666 | H9: =C9*1*(1+0.0256)^MAX(1,B9+(0))/(1+0.1056)^MAX(1,B9+(0)) -> 4212.3525 | I9: =C9*1*(1+0.0456)^MAX(1,B9+(0))/(1+0.0956)^MAX(1,B9+(0)) -> 4719.0979 | J9: =C9*1.01*(1+0.0356)^MAX(1,B9+(0))/(1+0.1056)^MAX(1,B9+(0)) -> 4422.8499 | K9: =C9*1.1*(1+0.0356)^MAX(1,B9+(0))/(1+0.1056)^MAX(1,B9+(0)) -> 4816.9653 | L9: =C9*1*(1+0.0356)^MAX(1,B9+(-2))/(1+0.1056)^MAX(1,B9+(-2)) -> 4991.0602 | M9: =C9*1*(1+0.0366)^MAX(1,B9+(0))/(1+0.1092)^MAX(1,B9+(0)) -> 4339.2049
A10: 2030 | B10: =A10-2025 -> 5 | C10: 7584.7893 | D10: =C10*1*(1+0.0356)^MAX(1,B10+(0))/(1+0.1056)^MAX(1,B10+(0)) -> 5469.0712 | E10: =C10*1*(1+0.0356)^MAX(1,B10+(0))/(1+0.1156)^MAX(1,B10+(0)) -> 5228.3084 | F10: =C10*1*(1+0.0356)^MAX(1,B10+(0))/(1+0.0956)^MAX(1,B10+(0)) -> 5723.2618 | G10: =C10*1*(1+0.0456)^MAX(1,B10+(0))/(1+0.1056)^MAX(1,B10+(0)) -> 5738.2735 | H10: =C10*1*(1+0.0256)^MAX(1,B10+(0))/(1+0.1056)^MAX(1,B10+(0)) -> 5210.0685 | I10: =C10*1*(1+0.0456)^MAX(1,B10+(0))/(1+0.0956)^MAX(1,B10+(0)) -> 6004.976 | J10: =C10*1.01*(1+0.0356)^MAX(1,B10+(0))/(1+0.1056)^MAX(1,B10+(0)) -> 5523.7619 | K10: =C10*1.1*(1+0.0356)^MAX(1,B10+(0))/(1+0.1056)^MAX(1,B10+(0)) -> 6015.9783 | L10: =C10*1*(1+0.0356)^MAX(1,B10+(-2))/(1+0.1056)^MAX(1,B10+(-2)) -> 6233.408 | M10: =C10*1*(1+0.0366)^MAX(1,B10+(0))/(1+0.1092)^MAX(1,B10+(0)) -> 5406.9237
A11: 2031 | B11: =A11-2025 -> 6 | C11: 9480.9866 | D11: =C11*1*(1+0.0356)^MAX(1,B11+(0))/(1+0.1056)^MAX(1,B11+(0)) -> 6403.5028 | E11: =C11*1*(1+0.0356)^MAX(1,B11+(0))/(1+0.1156)^MAX(1,B11+(0)) -> 6066.7311 | F11: =C11*1*(1+0.0356)^MAX(1,B11+(0))/(1+0.0956)^MAX(1,B11+(0)) -> 6762.2877 | G11: =C11*1*(1+0.0456)^MAX(1,B11+(0))/(1+0.1056)^MAX(1,B11+(0)) -> 6783.5776 | H11: =C11*1*(1+0.0256)^MAX(1,B11+(0))/(1+0.1056)^MAX(1,B11+(0)) -> 6041.342 | I11: =C11*1*(1+0.0456)^MAX(1,B11+(0))/(1+0.0956)^MAX(1,B11+(0)) -> 7163.6579 | J11: =C11*1.01*(1+0.0356)^MAX(1,B11+(0))/(1+0.1056)^MAX(1,B11+(0)) -> 6467.5378 | K11: =C11*1.1*(1+0.0356)^MAX(1,B11+(0))/(1+0.1056)^MAX(1,B11+(0)) -> 7043.8531 | L11: =C11*1*(1+0.0356)^MAX(1,B11+(-2))/(1+0.1056)^MAX(1,B11+(-2)) -> 7298.4322 | M11: =C11*1*(1+0.0366)^MAX(1,B11+(0))/(1+0.1092)^MAX(1,B11+(0)) -> 6316.2832
A12: 2032 | B12: =A12-2025 -> 7 | C12: 11377.184 | D12: =C12*1*(1+0.0356)^MAX(1,B12+(0))/(1+0.1056)^MAX(1,B12+(0)) -> 7197.6854 | E12: =C12*1*(1+0.0356)^MAX(1,B12+(0))/(1+0.1156)^MAX(1,B12+(0)) -> 6758.0209 | F12: =C12*1*(1+0.0356)^MAX(1,B12+(0))/(1+0.0956)^MAX(1,B12+(0)) -> 7670.3451 | G12: =C12*1*(1+0.0456)^MAX(1,B12+(0))/(1+0.1056)^MAX(1,B12+(0)) -> 7698.5262 | H12: =C12*1*(1+0.0256)^MAX(1,B12+(0))/(1+0.1056)^MAX(1,B12+(0)) -> 6725.0366 | I12: =C12*1*(1+0.0456)^MAX(1,B12+(0))/(1+0.0956)^MAX(1,B12+(0)) -> 8204.0752 | J12: =C12*1.01*(1+0.0356)^MAX(1,B12+(0))/(1+0.1056)^MAX(1,B12+(0)) -> 7269.6623 | K12: =C12*1.1*(1+0.0356)^MAX(1,B12+(0))/(1+0.1056)^MAX(1,B12+(0)) -> 7917.4539 | L12: =C12*1*(1+0.0356)^MAX(1,B12+(-2))/(1+0.1056)^MAX(1,B12+(-2)) -> 8203.6068 | M12: =C12*1*(1+0.0366)^MAX(1,B12+(0))/(1+0.1092)^MAX(1,B12+(0)) -> 7083.4394
A13: 2033 | B13: =A13-2025 -> 8 | C13: 13273.381 | D13: =C13*1*(1+0.0356)^MAX(1,B13+(0))/(1+0.1056)^MAX(1,B13+(0)) -> 7865.6327 | E13: =C13*1*(1+0.0356)^MAX(1,B13+(0))/(1+0.1156)^MAX(1,B13+(0)) -> 7318.9681 | F13: =C13*1*(1+0.0356)^MAX(1,B13+(0))/(1+0.0956)^MAX(1,B13+(0)) -> 8458.6628 | G13: =C13*1*(1+0.0456)^MAX(1,B13+(0))/(1+0.1056)^MAX(1,B13+(0)) -> 8494.1891 | H13: =C13*1*(1+0.0256)^MAX(1,B13+(0))/(1+0.1056)^MAX(1,B13+(0)) -> 7278.1571 | I13: =C13*1*(1+0.0456)^MAX(1,B13+(0))/(1+0.0956)^MAX(1,B13+(0)) -> 9134.6093 | J13: =C13*1.01*(1+0.0356)^MAX(1,B13+(0))/(1+0.1056)^MAX(1,B13+(0)) -> 7944.289 | K13: =C13*1.1*(1+0.0356)^MAX(1,B13+(0))/(1+0.1056)^MAX(1,B13+(0)) -> 8652.196 | L13: =C13*1*(1+0.0356)^MAX(1,B13+(-2))/(1+0.1056)^MAX(1,B13+(-2)) -> 8964.9039 | M13: =C13*1*(1+0.0366)^MAX(1,B13+(0))/(1+0.1092)^MAX(1,B13+(0)) -> 7723.1117
A14: 2034 | B14: =A14-2025 -> 9 | C14: 15169.579 | D14: =C14*1*(1+0.0356)^MAX(1,B14+(0))/(1+0.1056)^MAX(1,B14+(0)) -> 8420.146 | E14: =C14*1*(1+0.0356)^MAX(1,B14+(0))/(1+0.1156)^MAX(1,B14+(0)) -> 7764.7118 | F14: =C14*1*(1+0.0356)^MAX(1,B14+(0))/(1+0.0956)^MAX(1,B14+(0)) -> 9137.6323 | G14: =C14*1*(1+0.0456)^MAX(1,B14+(0))/(1+0.1056)^MAX(1,B14+(0)) -> 9180.8188 | H14: =C14*1*(1+0.0256)^MAX(1,B14+(0))/(1+0.1056)^MAX(1,B14+(0)) -> 7716.0202 | I14: =C14*1*(1+0.0456)^MAX(1,B14+(0))/(1+0.0956)^MAX(1,B14+(0)) -> 9963.1226 | J14: =C14*1.01*(1+0.0356)^MAX(1,B14+(0))/(1+0.1056)^MAX(1,B14+(0)) -> 8504.3474 | K14: =C14*1.1*(1+0.0356)^MAX(1,B14+(0))/(1+0.1056)^MAX(1,B14+(0)) -> 9262.1606 | L14: =C14*1*(1+0.0356)^MAX(1,B14+(-2))/(1+0.1056)^MAX(1,B14+(-2)) -> 9596.9139 | M14: =C14*1*(1+0.0366)^MAX(1,B14+(0))/(1+0.1092)^MAX(1,B14+(0)) -> 8248.7019
A15: 2035 | B15: =A15-2025 -> 10 | C15: 17065.776 | D15: =C15*1*(1+0.0356)^MAX(1,B15+(0))/(1+0.1056)^MAX(1,B15+(0)) -> 8872.9116 | E15: =C15*1*(1+0.0356)^MAX(1,B15+(0))/(1+0.1156)^MAX(1,B15+(0)) -> 8108.8898 | F15: =C15*1*(1+0.0356)^MAX(1,B15+(0))/(1+0.0956)^MAX(1,B15+(0)) -> 9716.8661 | G15: =C15*1*(1+0.0456)^MAX(1,B15+(0))/(1+0.1056)^MAX(1,B15+(0)) -> 9767.9063 | H15: =C15*1*(1+0.0256)^MAX(1,B15+(0))/(1+0.1056)^MAX(1,B15+(0)) -> 8052.4096 | I15: =C15*1*(1+0.0456)^MAX(1,B15+(0))/(1+0.0956)^MAX(1,B15+(0)) -> 10696.989 | J15: =C15*1.01*(1+0.0356)^MAX(1,B15+(0))/(1+0.1056)^MAX(1,B15+(0)) -> 8961.6407 | K15: =C15*1.1*(1+0.0356)^MAX(1,B15+(0))/(1+0.1056)^MAX(1,B15+(0)) -> 9760.2028 | L15: =C15*1*(1+0.0356)^MAX(1,B15+(-2))/(1+0.1056)^MAX(1,B15+(-2)) -> 10112.956 | M15: =C15*1*(1+0.0366)^MAX(1,B15+(0))/(1+0.1092)^MAX(1,B15+(0)) -> 8672.4034
A16: 2036 | B16: =A16-2025 -> 11 | C16: 18961.973 | D16: =C16*1*(1+0.0356)^MAX(1,B16+(0))/(1+0.1056)^MAX(1,B16+(0)) -> 9234.5908 | E16: =C16*1*(1+0.0356)^MAX(1,B16+(0))/(1+0.1156)^MAX(1,B16+(0)) -> 8363.7766 | F16: =C16*1*(1+0.0356)^MAX(1,B16+(0))/(1+0.0956)^MAX(1,B16+(0)) -> 10205.252 | G16: =C16*1*(1+0.0456)^MAX(1,B16+(0))/(1+0.1056)^MAX(1,B16+(0)) -> 10264.233 | H16: =C16*1*(1+0.0256)^MAX(1,B16+(0))/(1+0.1056)^MAX(1,B16+(0)) -> 8299.7179 | I16: =C16*1*(1+0.0456)^MAX(1,B16+(0))/(1+0.0956)^MAX(1,B16+(0)) -> 11343.122 | J16: =C16*1.01*(1+0.0356)^MAX(1,B16+(0))/(1+0.1056)^MAX(1,B16+(0)) -> 9326.9367 | K16: =C16*1.1*(1+0.0356)^MAX(1,B16+(0))/(1+0.1056)^MAX(1,B16+(0)) -> 10158.05 | L16: =C16*1*(1+0.0356)^MAX(1,B16+(-2))/(1+0.1056)^MAX(1,B16+(-2)) -> 10525.182 | M16: =C16*1*(1+0.0366)^MAX(1,B16+(0))/(1+0.1092)^MAX(1,B16+(0)) -> 9005.3025
A17: 2037 | B17: =A17-2025 -> 12 | C17: 20858.17 | D17: =C17*1*(1+0.0356)^MAX(1,B17+(0))/(1+0.1056)^MAX(1,B17+(0)) -> 9514.9028 | E17: =C17*1*(1+0.0356)^MAX(1,B17+(0))/(1+0.1156)^MAX(1,B17+(0)) -> 8540.4086 | F17: =C17*1*(1+0.0356)^MAX(1,B17+(0))/(1+0.0956)^MAX(1,B17+(0)) -> 10611.003 | G17: =C17*1*(1+0.0456)^MAX(1,B17+(0))/(1+0.1056)^MAX(1,B17+(0)) -> 10677.922 | H17: =C17*1*(1+0.0256)^MAX(1,B17+(0))/(1+0.1056)^MAX(1,B17+(0)) -> 8469.0754 | I17: =C17*1*(1+0.0456)^MAX(1,B17+(0))/(1+0.0956)^MAX(1,B17+(0)) -> 11908 | J17: =C17*1.01*(1+0.0356)^MAX(1,B17+(0))/(1+0.1056)^MAX(1,B17+(0)) -> 9610.0518 | K17: =C17*1.1*(1+0.0356)^MAX(1,B17+(0))/(1+0.1056)^MAX(1,B17+(0)) -> 10466.393 | L17: =C17*1*(1+0.0356)^MAX(1,B17+(-2))/(1+0.1056)^MAX(1,B17+(-2)) -> 10844.67 | M17: =C17*1*(1+0.0366)^MAX(1,B17+(0))/(1+0.1092)^MAX(1,B17+(0)) -> 9257.4705
... A30: 2050 | B30: =A30-2025 -> 25 | C30: 2413.342 | D30: =C30*1*(1+0.0356)^MAX(1,B30+(0))/(1+0.1056)^MAX(1,B30+(0)) -> 470.40201 | E30: =C30*1*(1+0.0356)^MAX(1,B30+(0))/(1+0.1156)^MAX(1,B30+(0)) -> 375.58417 | F30: =C30*1*(1+0.0356)^MAX(1,B30+(0))/(1+0.0956)^MAX(1,B30+(0)) -> 590.36327 | G30: =C30*1*(1+0.0456)^MAX(1,B30+(0))/(1+0.1056)^MAX(1,B30+(0)) -> 598.1464 | H30: =C30*1*(1+0.0256)^MAX(1,B30+(0))/(1+0.1056)^MAX(1,B30+(0)) -> 369.07823 | I30: =C30*1*(1+0.0456)^MAX(1,B30+(0))/(1+0.0956)^MAX(1,B30+(0)) -> 750.68485 | J30: =C30*1.01*(1+0.0356)^MAX(1,B30+(0))/(1+0.1056)^MAX(1,B30+(0)) -> 475.10603 | K30: =C30*1.1*(1+0.0356)^MAX(1,B30+(0))/(1+0.1056)^MAX(1,B30+(0)) -> 517.44221 | L30: =C30*1*(1+0.0356)^MAX(1,B30+(-2))/(1+0.1056)^MAX(1,B30+(-2)) -> 536.14363 | M30: =C30*1*(1+0.0366)^MAX(1,B30+(0))/(1+0.1092)^MAX(1,B30+(0)) -> 444.27561
A31: TOTAL | C31: =SUM(C6:C30) -> 336882.11 | D31: =SUM(D6:D30) -> 145192 | E31: =SUM(E6:E30) -> 130571.96 | F31: =SUM(F6:F30) -> 161993.69 | G31: =SUM(G6:G30) -> 163031.71 | H31: =SUM(H6:H30) -> 129513.49 | I31: =SUM(I6:I30) -> 182362.31 | J31: =SUM(J6:J30) -> 146643.92 | ... M31: =SUM(M6:M30) -> 141300.78

Sheet Sensibilidade
A1: Sensibilidade da provisao (NBC TA 540 itens 26 e 29; NBC TA 320 A11) - SIMULADO sobre cronograma calibrado
A2: PetroReconcavo S.A. - consolidado - R$ mil | Preparador: matricula 211059370 | 24/10/2026 | Revisao: ______ (nao preenchido)
A4: Cenario | B4: Provisao (PV) | C4: Variacao vs base | D4: % da ME | E4: % da MG | F4: Leitura
A5: Base (NE 3.3: 10,56% / 3,56%) | B5: =Cronograma_SIMULADO!D31 -> 145192 | C5: =B5-$B$5 -> 0 | D5: =C5/Premissas!$B$13 -> 0 | E5: =C5/Premissas!$B$14 -> 0 | F5: trivial
A6: Taxa de desconto +1 p.p. (11,56%) | B6: =Cronograma_SIMULADO!E31 -> 130571.96 | C6: =B6-$B$5 -> -14620.043 | D6: =C6/Premissas!$B$13 -> -0.71404363 | E6: =C6/Premissas!$B$14 -> -0.46412836 | F6: acima do trivial (1.575)
A7: Taxa de desconto -1 p.p. (9,56%) | B7: =Cronograma_SIMULADO!F31 -> 161993.69 | C7: =B7-$B$5 -> 16801.688 | D7: =C7/Premissas!$B$13 -> 0.82059526 | E7: =C7/Premissas!$B$14 -> 0.53338692 | F7: acima do trivial (1.575)
A8: Inflacao +1 p.p. (4,56%) | B8: =Cronograma_SIMULADO!G31 -> 163031.71 | C8: =B8-$B$5 -> 17839.711 | D8: =C8/Premissas!$B$13 -> 0.87129236 | E8: =C8/Premissas!$B$14 -> 0.56634003 | F8: acima do trivial (1.575)
A9: Inflacao -1 p.p. (2,56%) | B9: =Cronograma_SIMULADO!H31 -> 129513.49 | C9: =B9-$B$5 -> -15678.514 | D9: =C9/Premissas!$B$13 -> -0.76573939 | E9: =C9/Premissas!$B$14 -> -0.4977306 | F9: acima do trivial (1.575)
A10: Pior combinacao: taxa -1 p.p. e inflacao +1 p.p. | B10: =Cronograma_SIMULADO!I31 -> 182362.31 | C10: =B10-$B$5 -> 37170.31 | D10: =C10/Premissas!$B$13 -> 1.8153998 | E10: =C10/Premissas!$B$14 -> 1.1800098 | F10: acima da ME
A11: Custos +1% (sensibilidade de 1% - aula) | B11: =Cronograma_SIMULADO!J31 -> 146643.92 | C11: =B11-$B$5 -> 1451.92 | D11: =C11/Premissas!$B$13 -> 0.070911844 | E11: =C11/Premissas!$B$14 -> 0.046092698 | F11: trivial
A12: Custos +10% | B12: =Cronograma_SIMULADO!K31 -> 159711.2 | C12: =B12-$B$5 -> 14519.2 | D12: =C12/Premissas!$B$13 -> 0.70911844 | E12: =C12/Premissas!$B$14 -> 0.46092698 | F12: acima do trivial (1.575)
A13: Antecipacao de 2 anos no abandono | B13: =Cronograma_SIMULADO!L31 -> 164702.66 | C13: =B13-$B$5 -> 19510.664 | D13: =C13/Premissas!$B$13 -> 0.95290177 | E13: =C13/Premissas!$B$14 -> 0.61938615 | F13: acima do trivial (1.575)
A14: Premissas de 2024 (10,92% / 3,66%) sobre o mesmo cronograma | B14: =Cronograma_SIMULADO!M31 -> 141300.78 | C14: =B14-$B$5 -> -3891.2164 | D14: =C14/Premissas!$B$13 -> -0.1900472 | E14: =C14/Premissas!$B$14 -> -0.12353068 | F14: acima do trivial (1.575)
A16: Total nao descontado do cronograma (moeda 2025): 336.882
A17: Valores ILUSTRATIVOS: dependem do cronograma sintetico; a direcao e a ordem de grandeza servem para planejar o teste do item 24 e avaliar a divulgacao (item 26).
