Workbook

Sheet Resumo_testes_populacao
A1: Testes em 100% da populacao (T01-T10) - resumo
A2: DADOS SINTETICOS - procedimento SIMULADO PARA FINS DIDATICOS | Preparador: matricula 211059370 | Data: 23/10/2026 | Revisao: ______ (nao preenchido)
A4: Teste | B4: Qtd. excecoes | C4: Valor em risco (R$) | D4: Afirmacao | E4: Norma
A5: T01_DUPLICIDADE | B5: 160 | C5: 6737989.2 | D5: Existencia | E5: NBC TA 500 / 240
A6: T02_CORTE | B6: 46 | C6: 2502284.4 | D6: Existencia / corte | E6: NBC TA 500 / 330
A7: T03_VCL_NEGATIVO | B7: 40 | C7: -530782.38 | D7: Avaliacao | E7: NBC TA 500 / 520
A8: T04_RECALCULO_DEPRECIACAO | B8: 115 | C8: -444915.66 | D8: Avaliacao (exatidao) | E8: NBC TA 500 A21 (recalculo)
A9: T05_BAIXADO_COM_SALDO | B9: 63 | C9: 2553787.7 | D9: Existencia | E9: NBC TA 500
A10: T06_ALMOX_SEM_MOVIMENTO_5A | B10: 95 | C10: 281273.7 | D10: Avaliacao (recuperabilidade) | E10: NBC TA 540 / 501
A11: T07_MAKER_CHECKER | B11: 627 | C11: 0 | D11: Controle - segregacao | E11: NBC TA 315 / 265
A12: T08_CAMPO_NAO_CADASTRADO | B12: 35 | C12: 1234406.1 | D12: Existencia / classificacao | E12: NBC TA 500 / 240
A13: T09_ANDAMENTO_PARADO_2A | B13: 45 | C13: 1134210 | D13: Avaliacao / classificacao | E13: NBC TA 540
A14: T10_DATA_ANTERIOR_CONSTITUICAO | B14: 30 | C14: 0 | D14: Integridade cadastral | E14: NBC TA 500 (confiabilidade dos dados)

Sheet Excecoes_detalhe
A1: Detalhe das excecoes (todas)
A2: DADOS SINTETICOS - procedimento SIMULADO PARA FINS DIDATICOS | Preparador: matricula 211059370 | Data: 23/10/2026 | Revisao: ______ (nao preenchido)
A4: teste | B4: id_registro | C4: classe_ne7 | D4: valor_contabil_liquido | E4: valor_em_risco | F4: detalhe
A5: T01_DUPLICIDADE | B5: IMB-0143037 | C5: ALMOXARIFADO_INVERSOES_FIXAS | D5: 1012.46 | E5: 1012.46 | F5: Mesmo documento/fornecedor/valor/data de outro registro (cadastro posterior)
A6: T01_DUPLICIDADE | B6: IMB-0254231 | C6: ALMOXARIFADO_INVERSOES_FIXAS | D6: 3074.45 | E6: 3074.45 | F6: Mesmo documento/fornecedor/valor/data de outro registro (cadastro posterior)
A7: T01_DUPLICIDADE | B7: IMB-0504710 | C7: ALMOXARIFADO_INVERSOES_FIXAS | D7: 3901.8 | E7: 3901.8 | F7: Mesmo documento/fornecedor/valor/data de outro registro (cadastro posterior)
A8: T01_DUPLICIDADE | B8: IMB-0069260 | C8: ALMOXARIFADO_INVERSOES_FIXAS | D8: 1174.27 | E8: 1174.27 | F8: Mesmo documento/fornecedor/valor/data de outro registro (cadastro posterior)
A9: T01_DUPLICIDADE | B9: IMB-0095632 | C9: ALMOXARIFADO_INVERSOES_FIXAS | D9: 19036.91 | E9: 19036.91 | F9: Mesmo documento/fornecedor/valor/data de outro registro (cadastro posterior)
A10: T01_DUPLICIDADE | B10: IMB-0094369 | C10: ALMOXARIFADO_INVERSOES_FIXAS | D10: 919.05 | E10: 919.05 | F10: Mesmo documento/fornecedor/valor/data de outro registro (cadastro posterior)
A11: T01_DUPLICIDADE | B11: IMB-0031758 | C11: ALMOXARIFADO_INVERSOES_FIXAS | D11: 1716.9 | E11: 1716.9 | F11: Mesmo documento/fornecedor/valor/data de outro registro (cadastro posterior)
A12: T01_DUPLICIDADE | B12: IMB-0022000 | C12: ALMOXARIFADO_INVERSOES_FIXAS | D12: 368.52 | E12: 368.52 | F12: Mesmo documento/fornecedor/valor/data de outro registro (cadastro posterior)
A13: T01_DUPLICIDADE | B13: IMB-0383385 | C13: ALMOXARIFADO_INVERSOES_FIXAS | D13: 2258.15 | E13: 2258.15 | F13: Mesmo documento/fornecedor/valor/data de outro registro (cadastro posterior)
A14: T01_DUPLICIDADE | B14: IMB-0381741 | C14: ALMOXARIFADO_INVERSOES_FIXAS | D14: 64351.15 | E14: 64351.15 | F14: Mesmo documento/fornecedor/valor/data de outro registro (cadastro posterior)
A15: T01_DUPLICIDADE | B15: IMB-0481420 | C15: ALMOXARIFADO_INVERSOES_FIXAS | D15: 1618.49 | E15: 1618.49 | F15: Mesmo documento/fornecedor/valor/data de outro registro (cadastro posterior)
A16: T01_DUPLICIDADE | B16: IMB-0280601 | C16: ALMOXARIFADO_INVERSOES_FIXAS | D16: 674.63 | E16: 674.63 | F16: Mesmo documento/fornecedor/valor/data de outro registro (cadastro posterior)
... A1260: T10_DATA_ANTERIOR_CONSTITUICAO | B1260: IMB-0484115 | C1260: OUTROS | D1260: 162.58 | E1260: 0 | F1260: Data de aquisicao anterior a 21/07/1999

Sheet MUS_parametros
A1: MUS - parametros e intervalo (Gramling cap. 8; NBC TA 530) - formulas editaveis
A2: DADOS SINTETICOS - procedimento SIMULADO PARA FINS DIDATICOS | Preparador: matricula 211059370 | Data: 23/10/2026 | Revisao: ______ (nao preenchido)
A4: Parametro | B4: Valor | C4: Fonte / formula
A5: Materialidade global provisoria - MG (R$) | B5: 31500000 | C5: PT 320: 1% da receita liquida consolidada 2025 (R$ 3.157.609 mil) = 31.576 mil, arredondado p/ baixo (NBC TA 320 itens 10, A5, A8)
A6: % da MG para execucao | B6: 0.65 | C6: Julgamento (NBC TA 320 item 11 e A13): primeira auditoria + inconsistencias de divulgacao + risco de impairment
A7: Materialidade para execucao - ME (R$) | B7: =B5*B6 | C7: MG x %
A8: Incorrecao toleravel - IT (R$) | B8: =B7 | C8: IT = ME (sem materialidade especifica para o imobilizado)
A9: % IT para incorrecao esperada | B9: 0.1 | C9: Premissa do auditor (sem historico: primeira auditoria)
A10: Incorrecao esperada - IE (R$) | B10: =B8*B9 | C10: IT x %
A11: Risco de auditoria - RA | B11: 0.05 | C11: Gramling: RA = RI x RC x RD
A12: Risco inerente - RI | B12: 1 | C12: Maximo: estimativas e julgamentos (PT 315)
A13: Risco de controle - RC | B13: 1 | C13: Maximo: controles nao testados (sem acesso)
A14: Risco de deteccao - RD | B14: =B11/(B12*B13) | C14: RD = RA / (RI x RC)
A15: Coluna da Ilustracao 8.7 utilizada | B15: 0.05 | C15: RD da tabela imediatamente inferior ou igual ao calculado
A16: Fator de confiabilidade - FC | B16: 3 | C16: Ilustracao 8.7
A17: Fator de expansao de erro - FEE | B17: 1.6 | C17: Ilustracao 8.7
A18: Intervalo de amostragem - I (R$) | B18: =(B8-B10*B17)/B16 | C18: I = (IT - IE x FEE) / FC
A19: Valor contabil da populacao (VCL > 0) (R$) | B19: 6.1713701e+09 | C19: 517.770 itens; itens com VCL <= 0 testados a parte (T03)
A20: Tamanho maximo da amostra - n | B20: =B19/B18 | C20: n = valor contabil / I
A21: Ponto de partida aleatorio (R$) | B21: 3429906.8 | C21: Gerador numpy, semente 211059900 (entre 1 e I)
A22: Pontos de selecao | B22: 1076 | C22: inicio + k x I
A23: Itens distintos selecionados | B23: 772 | C23: itens com mais de um ponto contam uma vez
A24: Itens do estrato superior (VC >= I) | B24: 56 | C24: selecao certa (100%)
A27: Ilustracao 8.7 (Gramling) - fatores
A28: Risco de deteccao | B28: FC | C28: FEE | D28: Incr. 1 | E28: Incr. 2 | F28: Incr. 3 | G28: Incr. 4 | H28: Incr. 5 | I28: Incr. 6 | J28: Incr. 7 | K28: Incr. 8 | L28: Incr. 9 | M28: Incr. 10
A29: 0.01 | B29: 4.61 | C29: 1.9 | D29: 1.03 | E29: 0.77 | F29: 0.64 | G29: 0.56 | H29: 0.5 | I29: 0.46 | J29: 0.43 | K29: 0.41 | L29: 0.38 | M29: 0.38
A30: 0.05 | B30: 3 | C30: 1.6 | D30: 0.75 | E30: 0.55 | F30: 0.46 | G30: 0.4 | H30: 0.36 | I30: 0.33 | J30: 0.3 | K30: 0.29 | L30: 0.27 | M30: 0.26
A31: 0.1 | B31: 2.31 | C31: 1.5 | D31: 0.58 | E31: 0.44 | F31: 0.36 | G31: 0.31 | H31: 0.28 | I31: 0.26 | J31: 0.24 | K31: 0.22 | L31: 0.21 | M31: 0.2
A32: 0.15 | B32: 1.9 | C32: 1.4 | D32: 0.48 | E32: 0.34 | F32: 0.3 | G32: 0.25 | H32: 0.23 | I32: 0.21 | J32: 0.19 | K32: 0.18 | L32: 0.17 | M32: 0.17
A33: 0.2 | B33: 1.61 | C33: 1.3 | D33: 0.39 | E33: 0.28 | F33: 0.24 | G33: 0.21 | H33: 0.18 | I33: 0.17 | J33: 0.16 | K33: 0.14 | L33: 0.14 | M33: 0.14
A34: 0.25 | B34: 1.39 | C34: 1.25 | D34: 0.31 | E34: 0.23 | F34: 0.18 | G34: 0.17 | H34: 0.15 | I34: 0.13 | J34: 0.13 | K34: 0.12 | L34: 0.11 | M34: 0.1
A35: 0.3 | B35: 1.21 | C35: 1.2 | D35: 0.23 | E35: 0.18 | F35: 0.15 | G35: 0.13 | H35: 0.11 | I35: 0.11 | J35: 0.1 | K35: 0.09 | L35: 0.08 | M35: 0.08
A36: 0.5 | B36: 0.7 | C36: 1 | D36: 0 | E36: 0 | F36: 0 | G36: 0 | H36: 0 | I36: 0 | J36: 0 | K36: 0 | L36: 0 | M36: 0

Sheet MUS_amostra
A1: MUS - itens selecionados e resultado da inspecao documental SIMULADA
A2: DADOS SINTETICOS - procedimento SIMULADO PARA FINS DIDATICOS | Preparador: matricula 211059370 | Data: 23/10/2026 | Revisao: ______ (nao preenchido)
A4: id_registro | B4: classe_ne7 | C4: conta_custo | D4: campo | E4: tipo_item | F4: estrato | G4: pontos_no_item | H4: primeiro_ponto | I4: acumulado | J4: valor_contabil_liquido | K4: documento_localizado | L4: data_documento | M4: valor_auditado | N4: incorrecao | O4: tainting | P4: incorrecao_projetada | Q4: observacao_inspecao
A5: IMB-0000473 | B5: DESENVOLVIMENTO_CAMPOS | C5: 1.2.03.04.002 | D5: POT-CONC-06 (SINTETICO) | E5: FRATURAMENTO / ESTIMULACAO CAPITALIZADA | F5: INFERIOR | G5: 1 | H5: 3429906.8 | I5: 3430542.1 | J5: 21543.33 | K5: S | L5: 2023-09-10 | M5: 21543.33 | N5: =J5-M5 | O5: =IF(F5="INFERIOR",N5/J5,"") | P5: =IF(F5="INFERIOR",O5*MUS_parametros!$B$18,N5) | Q5: Documento confere com o registro
A6: IMB-0001323 | B6: DESENVOLVIMENTO_CAMPOS | C6: 1.2.03.04.001 | D6: CANABRAVA | E6: PERFURACAO E COMPLETACAO | F6: INFERIOR | G6: 1 | H6: 9162906.8 | I6: 9185062.6 | J6: 30397.2 | K6: S | L6: 2024-02-07 | M6: 30397.2 | N6: =J6-M6 | O6: =IF(F6="INFERIOR",N6/J6,"") | P6: =IF(F6="INFERIOR",O6*MUS_parametros!$B$18,N6) | Q6: Documento confere com o registro
A7: IMB-0002284 | B7: DESENVOLVIMENTO_CAMPOS | C7: 1.2.03.04.001 | D7: POT-CONC-18 (SINTETICO) | E7: PERFURACAO E COMPLETACAO | F7: INFERIOR | G7: 1 | H7: 14895907 | I7: 14905870 | J7: 24426.34 | K7: S | L7: 2024-08-28 | M7: 24426.34 | N7: =J7-M7 | O7: =IF(F7="INFERIOR",N7/J7,"") | P7: =IF(F7="INFERIOR",O7*MUS_parametros!$B$18,N7) | Q7: Documento confere com o registro
A8: IMB-0003118 | B8: DESENVOLVIMENTO_CAMPOS | C8: 1.2.03.04.001 | D8: JACUIPE | E8: PERFURACAO E COMPLETACAO | F8: INFERIOR | G8: 1 | H8: 20628907 | I8: 20816752 | J8: 601235.02 | K8: S | L8: 2025-06-02 | M8: 601235.02 | N8: =J8-M8 | O8: =IF(F8="INFERIOR",N8/J8,"") | P8: =IF(F8="INFERIOR",O8*MUS_parametros!$B$18,N8) | Q8: Documento confere com o registro
A9: IMB-0003892 | B9: DESENVOLVIMENTO_CAMPOS | C9: 1.2.03.04.001 | D9: TARTARUGA | E9: PERFURACAO E COMPLETACAO | F9: INFERIOR | G9: 1 | H9: 26361907 | I9: 26514305 | J9: 812160.05 | K9: S | L9: 2025-08-04 | M9: 812160.05 | N9: =J9-M9 | O9: =IF(F9="INFERIOR",N9/J9,"") | P9: =IF(F9="INFERIOR",O9*MUS_parametros!$B$18,N9) | Q9: Documento confere com o registro
A10: IMB-0004632 | B10: DESENVOLVIMENTO_CAMPOS | C10: 1.2.03.04.001 | D10: POT-CONC-12 (SINTETICO) | E10: PERFURACAO E COMPLETACAO | F10: INFERIOR | G10: 1 | H10: 32094907 | I10: 32635639 | J10: 557888.69 | K10: S | L10: 2025-12-27 | M10: 557888.69 | N10: =J10-M10 | O10: =IF(F10="INFERIOR",N10/J10,"") | P10: =IF(F10="INFERIOR",O10*MUS_parametros!$B$18,N10) | Q10: Documento confere com o registro
A11: IMB-0005316 | B11: DESENVOLVIMENTO_CAMPOS | C11: 1.2.03.04.003 | D11: RIO SUBAUMA | E11: BOMBA DE FUNDO (BM/BCP) | F11: INFERIOR | G11: 1 | H11: 37827907 | I11: 37828425 | J11: 1071.44 | K11: S | L11: 2025-03-06 | M11: 1071.44 | N11: =J11-M11 | O11: =IF(F11="INFERIOR",N11/J11,"") | P11: =IF(F11="INFERIOR",O11*MUS_parametros!$B$18,N11) | Q11: Documento confere com o registro
A12: IMB-0005800 | B12: DESENVOLVIMENTO_CAMPOS | C12: 1.2.03.04.001 | D12: POT-CONC-02 (SINTETICO) | E12: PERFURACAO E COMPLETACAO | F12: INFERIOR | G12: 1 | H12: 43560907 | I12: 43588199 | J12: 256928.04 | K12: S | L12: 2024-11-29 | M12: 256928.04 | N12: =J12-M12 | O12: =IF(F12="INFERIOR",N12/J12,"") | P12: =IF(F12="INFERIOR",O12*MUS_parametros!$B$18,N12) | Q12: Documento confere com o registro
A13: IMB-0006566 | B13: MAQUINAS_EQUIPAMENTOS | C13: 1.2.03.01.004 | D13: UPGN GUAMARE | E13: UTILIDADES E INSTRUMENTACAO | F13: INFERIOR | G13: 1 | H13: 49293907 | I13: 49352254 | J13: 189761.9 | K13: S | L13: 2025-09-30 | M13: 189761.9 | N13: =J13-M13 | O13: =IF(F13="INFERIOR",N13/J13,"") | P13: =IF(F13="INFERIOR",O13*MUS_parametros!$B$18,N13) | Q13: Documento confere com o registro
A14: IMB-0006828 | B14: DIREITO_PRODUCAO_OLEO_GAS | C14: 1.2.03.03.001 | D14: SAO PEDRO | E14: CUSTO DE AQUISICAO DA CONCESSAO | F14: SUPERIOR (VC >= I) | G14: 1 | H14: 55026907 | I14: 59073151 | J14: 7042726.9 | K14: S | L14: 2021-12-23 | M14: 7042726.9 | N14: =J14-M14 | O14: =IF(F14="INFERIOR",N14/J14,"") | P14: =IF(F14="INFERIOR",O14*MUS_parametros!$B$18,N14) | Q14: Documento confere com o registro
A15: IMB-0007038 | B15: DESENVOLVIMENTO_CAMPOS | C15: 1.2.03.04.001 | D15: LAGOA DO PAULO | E15: PERFURACAO E COMPLETACAO | F15: INFERIOR | G15: 1 | H15: 60759907 | I15: 61029682 | J15: 303067.73 | K15: S | L15: 2023-07-29 | M15: 303067.73 | N15: =J15-M15 | O15: =IF(F15="INFERIOR",N15/J15,"") | P15: =IF(F15="INFERIOR",O15*MUS_parametros!$B$18,N15) | Q15: Documento confere com o registro
A16: IMB-0007832 | B16: MAQUINAS_EQUIPAMENTOS | C16: 1.2.03.01.005 | D16: BREJINHO | E16: VEICULO PESADO / CAMINHAO SONDA | F16: INFERIOR | G16: 1 | H16: 66492907 | I16: 66525879 | J16: 42932.01 | K16: S | L16: 2024-07-06 | M16: 42932.01 | N16: =J16-M16 | O16: =IF(F16="INFERIOR",N16/J16,"") | P16: =IF(F16="INFERIOR",O16*MUS_parametros!$B$18,N16) | Q16: Documento confere com o registro
... A776: IMB-0531805 | B776: DESENVOLVIMENTO_CAMPOS | C776: 1.2.03.04.001 | D776: POT-CONC-08 (SINTETICO) | E776: PERFURACAO E COMPLETACAO | F776: INFERIOR | G776: 1 | H776: 6.1664049e+09 | I776: 6.1664266e+09 | J776: 185555.76 | K776: S | L776: 2024-05-17 | M776: 185555.76 | N776: =J776-M776 | O776: =IF(F776="INFERIOR",N776/J776,"") | P776: =IF(F776="INFERIOR",O776*MUS_parametros!$B$18,N776) | Q776: Documento confere com o registro

Sheet MUS_avaliacao
A1: MUS - avaliacao: LSI = precisao basica + incorrecao mais provavel + ajuste incremental
A2: DADOS SINTETICOS - procedimento SIMULADO PARA FINS DIDATICOS | Preparador: matricula 211059370 | Data: 23/10/2026 | Revisao: ______ (nao preenchido)
A4: Componente | B4: Valor (R$) | C4: Formula / explicacao
A5: Precisao basica (PB) | B5: =MUS_parametros!B16*MUS_parametros!$B$18 | C5: FC x I (LSI se nenhum erro fosse encontrado)
A6: Incorrecao mais provavel - estrato inferior (projetada) | B6: =SUMIFS(MUS_amostra!P5:P776,MUS_amostra!F5:F776,"INFERIOR",MUS_amostra!N5:N776,">0") | C6: soma de tainting x I
A7: Incorrecao - estrato superior (real, sem projecao) | B7: =SUMIFS(MUS_amostra!N5:N776,MUS_amostra!F5:F776,"<>INFERIOR",MUS_amostra!N5:N776,">0") | C7: diferenca efetiva
A8: Incorrecao mais provavel (IMP) | B8: =B6+B7 | C8: projetada + real
A9: Ajuste incremental (IA) | B9: =SUM(E13:E200) | C9: taintings em ordem decrescente x fator incremental x I (tabela abaixo)
A10: LIMITE SUPERIOR DE INCORRECAO (LSI) | B10: =B5+B8+B9 | C10: PB + IMP + IA
A11: Incorrecao toleravel (IT) | B11: =MUS_parametros!B8
A12: Ordem | B12: id_registro | C12: Tainting | D12: Fator incremental (col. RD) | E12: Ajuste incremental (R$)
A13: 1 | B13: IMB-0033499 | C13: 1 | D13: 0.75 | E13: =C13*D13*MUS_parametros!$B$18
A14: 2 | B14: IMB-0262098 | C14: 1 | D14: 0.55 | E14: =C14*D14*MUS_parametros!$B$18
A15: 3 | B15: IMB-0468355 | C15: 1 | D15: 0.46 | E15: =C15*D15*MUS_parametros!$B$18
A16: 4 | B16: IMB-0469519 | C16: 0.63013472 | D16: 0.4 | E16: =C16*D16*MUS_parametros!$B$18
A17: 5 | B17: IMB-0471357 | C17: 0.10730455 | D17: 0.36 | E17: =C17*D17*MUS_parametros!$B$18
A19: Premissa: a Ilustracao 8.7 traz fatores ate o 10o erro; para erros adicionais foi usado o ultimo fator da coluna (premissa conservadora documentada).
A20: Subavaliacoes (valor auditado > contabil) nao entram no LSI de superavaliacao; sao avaliadas a parte no PT 450.
A21: Resultado calculado em Python (conferencia): PB=17,199,000.00; IMP=21,426,739.36; IA=11,756,568.66; LSI=50,382,308.03; IT=20,475,000.00.

Sheet Inseridos_x_detectados
A1: Comparacao: erros INSERIDOS (log de controle) x DETECTADOS pelos testes
A2: DADOS SINTETICOS - procedimento SIMULADO PARA FINS DIDATICOS | Preparador: matricula 211059370 | Data: 23/10/2026 | Revisao: ______ (nao preenchido)
A4: tipo_erro | B4: descricao | C4: teste | D4: inseridos | E4: detectados_pelo_teste | F4: verdadeiros_positivos | G4: nao_detectados | H4: detectados_de_outro_tipo_inserido | I4: falsos_positivos | J4: taxa_deteccao | K4: efeito_inserido
A5: E01 | B5: Registro duplicado (mesmo documento, fornecedor, valor e data de aquisicao do registro original) | C5: T01_DUPLICIDADE | D5: 160 | E5: 160 | F5: 160 | G5: 0 | H5: 0 | I5: 0 | J5: 1 | K5: 6737989.2
A6: E02 | B6: Corte: data de aquisicao/capitalizacao posterior a 31/12/2025 (item nao existia na data-base) | C6: T02_CORTE | D6: 46 | E6: 46 | F6: 46 | G6: 0 | H6: 0 | I6: 0 | J6: 1 | K6: 2502284.4
A7: E03 | B7: Depreciacao acumulada superior ao custo (valor contabil liquido negativo) | C7: T03_VCL_NEGATIVO | D7: 40 | E7: 40 | F7: 40 | G7: 0 | H7: 0 | I7: 0 | J7: 1 | K7: -530782.38
A8: E04 | B8: Depreciacao acumulada registrada a menor que o recalculo (taxa x tempo de uso) | C8: T04_RECALCULO_DEPRECIACAO | D8: 70 | E8: 115 | F8: 70 | G8: 0 | H8: 45 | I8: 0 | J8: 1 | K8: 1511583.8
A9: E05 | B9: Item com status BAIXADO (baixa em 2025) mantido com saldo no subrazao | C9: T05_BAIXADO_COM_SALDO | D9: 63 | E9: 63 | F9: 63 | G9: 0 | H9: 0 | I9: 0 | J9: 1 | K9: 2553787.7
A10: E06 | B10: Material de almoxarifado de investimento sem movimentacao ha mais de 5 anos (indicio de obsolescencia) | C10: T06_ALMOX_SEM_MOVIMENTO_5A | D10: 95 | E10: 95 | F10: 95 | G10: 0 | H10: 0 | I10: 0 | J10: 1 | K10: 0
A11: E07 | B11: Cadastro sem aprovacao (campo usuario_aprovacao vazio) | C11: T07_MAKER_CHECKER | D11: 620 | E11: 627 | F11: 620 | G11: 0 | H11: 7 | I11: 0 | J11: 1 | K11: 0
A12: E08 | B12: Campo nao cadastrado entre as 58 concessoes e documento de suporte inexistente (existencia) | C12: T08_CAMPO_NAO_CADASTRADO | D12: 35 | E12: 35 | F12: 35 | G12: 0 | H12: 0 | I12: 0 | J12: 1 | K12: 1234406.1
A13: E09 | B13: Custo registrado acima do suportado por documento (inclui despesa de manutencao capitalizada) | C13: MUS (inspecao documental) | D13: 97 | E13: 5 | F13: 2 | G13: 95 | H13: 3 | I13: 0 | J13: 0.020618557 | K13: 9172612
A14: E10 | B14: Ordem em andamento sem movimentacao ha mais de 2 anos | C14: T09_ANDAMENTO_PARADO_2A | D14: 45 | E14: 45 | F14: 45 | G14: 0 | H14: 0 | I14: 0 | J14: 1 | K14: 0
A15: E11 | B15: Data de aquisicao anterior a constituicao da companhia (21/07/1999) - erro cadastral | C15: T10_DATA_ANTERIOR_CONSTITUICAO | D15: 30 | E15: 30 | F15: 30 | G15: 0 | H15: 0 | I15: 0 | J15: 1 | K15: 0
A18: MUS: incorrecao mais provavel projetada = R$ 21,426,739.36; LSI = R$ 50,382,308.03.
A19: Superavaliacao total efetivamente inserida na base (todos os tipos monetarios) = R$ 23,712,663.10.
A20: O LSI cobre a superavaliacao real inserida - validacao didatica do metodo.
A21: Os testes T01-T10 foram executados antes da leitura do log (as cegas); o log foi usado apenas nesta aba.
